jillw/__init__.py
jillw/cli.py
jillw/configloader.py
jillw-0.3.1.dist-info/entry_points.txt
jillw-0.3.1.dist-info/LICENSE.md
jillw-0.3.1.dist-info/METADATA
jillw-0.3.1.dist-info/WHEEL
jillw-0.3.1.dist-info/RECORD
