Metadata-Version: 2.1
Name: jillw
Version: 0.3.1
Summary: The wrapper for jill.py and manage Julia environments with Python virtualenv
License: MIT
Author: Suzhou-tongyuan
Author-email: support@tongyuan.cc
Requires-Python: >=3.8,<4.0
Classifier: License :: OSI Approved :: MIT License
Classifier: Programming Language :: Python :: 3
Classifier: Programming Language :: Python :: 3.8
Classifier: Programming Language :: Python :: 3.9
Classifier: Programming Language :: Python :: 3.10
Classifier: Programming Language :: Python :: 3.11
Requires-Dist: jill (>=0.11.1,<0.12.0)
Requires-Dist: tomli (>=2.0.1,<3.0.0)
Requires-Dist: wisepy2 (>=1.3,<2.0)
